Xlib/X.py
Xlib/XK.py
Xlib/Xatom.py
Xlib/Xcursorfont.py
Xlib/Xutil.py
Xlib/__init__.py
Xlib/display.py
Xlib/error.py
Xlib/rdb.py
Xlib/threaded.py
Xlib/xauth.py
Xlib/ext/__init__.py
Xlib/ext/composite.py
Xlib/ext/ge.py
Xlib/ext/randr.py
Xlib/ext/record.py
Xlib/ext/security.py
Xlib/ext/shape.py
Xlib/ext/xfixes.py
Xlib/ext/xinerama.py
Xlib/ext/xinput.py
Xlib/ext/xtest.py
Xlib/keysymdef/__init__.py
Xlib/keysymdef/apl.py
Xlib/keysymdef/arabic.py
Xlib/keysymdef/cyrillic.py
Xlib/keysymdef/greek.py
Xlib/keysymdef/hebrew.py
Xlib/keysymdef/katakana.py
Xlib/keysymdef/korean.py
Xlib/keysymdef/latin1.py
Xlib/keysymdef/latin2.py
Xlib/keysymdef/latin3.py
Xlib/keysymdef/latin4.py
Xlib/keysymdef/miscellany.py
Xlib/keysymdef/publishing.py
Xlib/keysymdef/special.py
Xlib/keysymdef/technical.py
Xlib/keysymdef/thai.py
Xlib/keysymdef/xf86.py
Xlib/keysymdef/xk3270.py
Xlib/keysymdef/xkb.py
Xlib/protocol/__init__.py
Xlib/protocol/display.py
Xlib/protocol/event.py
Xlib/protocol/request.py
Xlib/protocol/rq.py
Xlib/protocol/structs.py
Xlib/support/__init__.py
Xlib/support/connect.py
Xlib/support/lock.py
Xlib/support/unix_connect.py
Xlib/support/vms_connect.py
Xlib/xobject/__init__.py
Xlib/xobject/colormap.py
Xlib/xobject/cursor.py
Xlib/xobject/drawable.py
Xlib/xobject/fontable.py
Xlib/xobject/icccm.py
Xlib/xobject/resource.py
pyxlib-0.21.dist-info/DESCRIPTION.rst
pyxlib-0.21.dist-info/METADATA
pyxlib-0.21.dist-info/RECORD
pyxlib-0.21.dist-info/WHEEL
pyxlib-0.21.dist-info/metadata.json
pyxlib-0.21.dist-info/top_level.txt
